geodataflow/pipelineapp.default.settings
geodataflow/pipelineapp.py
geodataflow/core/__init__.py
geodataflow/core/__meta__.py
geodataflow/core/capabilities.py
geodataflow/core/common.py
geodataflow/core/jsoncomments.py
geodataflow/core/modulemanager.py
geodataflow/core/processing.py
geodataflow/core/progress.py
geodataflow/core/relationships.py
geodataflow/core/schemadef.py
geodataflow/core/settingsmanager.py
geodataflow/core/modules/ConnectionJoin.py
geodataflow/core/modules/InputParam.py
geodataflow/pipeline/__init__.py
geodataflow/pipeline/basictypes.py
geodataflow/pipeline/datastagetypes.py
geodataflow/pipeline/moduledef.py
geodataflow/pipeline/pipelinecontext.py
geodataflow/pipeline/pipelinemanager.py
geodataflow.core-0.2.1.dist-info/LICENSE
geodataflow.core-0.2.1.dist-info/METADATA
geodataflow.core-0.2.1.dist-info/WHEEL
geodataflow.core-0.2.1.dist-info/dependency_links.txt
geodataflow.core-0.2.1.dist-info/entry_points.txt
geodataflow.core-0.2.1.dist-info/top_level.txt
geodataflow.core-0.2.1.dist-info/RECORD
